sayit/__init__.py
sayit/cli.py
sayit/say.py
sayit-0.1.0.dist-info/AUTHORS.rst
sayit-0.1.0.dist-info/LICENSE
sayit-0.1.0.dist-info/METADATA
sayit-0.1.0.dist-info/WHEEL
sayit-0.1.0.dist-info/entry_points.txt
sayit-0.1.0.dist-info/top_level.txt
sayit-0.1.0.dist-info/RECORD
