Metadata-Version: 2.1
Name: sayit
Version: 0.1.0
Summary: This simple package makes it easy to say big numbers
Home-page: https://github.com/samarpan-rai/sayit
Author: Samarpan Rai
Author-email: samarpan-rai@live.com
License: MIT license
Keywords: sayit
Platform: UNKNOWN
Classifier: Development Status :: 2 - Pre-Alpha
Classifier: Intended Audience :: Developers
Classifier: License :: OSI Approved :: MIT License
Classifier: Natural Language :: English
Classifier: Programming Language :: Python :: 3
Classifier: Programming Language :: Python :: 3.5
Classifier: Programming Language :: Python :: 3.6
Classifier: Programming Language :: Python :: 3.7
Classifier: Programming Language :: Python :: 3.8
Requires-Python: >=3.5
Requires-Dist: Click (>=7.0)
